generic_rest_client/__init__.py
generic_rest_client/__version__.py
generic_rest_client/client.py
generic_rest_client/exceptions.py
generic_rest_client-0.2.1.dist-info/LICENCE
generic_rest_client-0.2.1.dist-info/METADATA
generic_rest_client-0.2.1.dist-info/WHEEL
generic_rest_client-0.2.1.dist-info/top_level.txt
generic_rest_client-0.2.1.dist-info/RECORD
