Metadata-Version: 2.1
Name: generic-rest-client
Version: 0.2.1
Summary: A generic and simple REST client for your python projects.
Home-page: https://github.com/Tpaga/generic_rest_client
Author: Tpaga
Author-email: devs@tpaga.co
License: MIT
Platform: UNKNOWN
Classifier: License :: OSI Approved :: MIT License
Classifier: Programming Language :: Python
Classifier: Programming Language :: Python :: 3
Classifier: Programming Language :: Python :: 3.6
Classifier: Programming Language :: Python :: Implementation :: CPython
Classifier: Programming Language :: Python :: Implementation :: PyPy
Requires-Python: >=3.6.0
Requires-Dist: requests
